{
  "date": "2026/04/15 15:09:09",
  "source": "GitHub Actions",
  "list": [
    {
      "id": "1313",
      "name": "聯成",
      "group": "塑膠",
      "type": "上市",
      "price": 12.65,
      "ma5": 12.46,
      "ma10": 12.45,
      "changeRate": -4.17,
      "isValid": true,
      "note": "Strict-VCP / MA300 9.77",
      "buy_price": 12.65,
      "latest_price": 12.65,
      "roi": 0.0,
      "daily_change": -4.17,
      "perf_1d": null,
      "perf_5d": null,
      "perf_10d": null,
      "perf_20d": null,
      "perf_30d": null,
      "perf_60d": null,
      "perf_120d": null
    },
    {
      "id": "1709",
      "name": "和益",
      "group": "化學工業",
      "type": "上市",
      "price": 19.1,
      "ma5": 18.87,
      "ma10": 18.4,
      "changeRate": -1.29,
      "isValid": true,
      "note": "拉回佈局 / MA300 17.47",
      "buy_price": 19.1,
      "latest_price": 19.1,
      "roi": 0.0,
      "daily_change": -1.29,
      "perf_1d": null,
      "perf_5d": null,
      "perf_10d": null,
      "perf_20d": null,
      "perf_30d": null,
      "perf_60d": null,
      "perf_120d": null
    },
    {
      "id": "2010",
      "name": "春源",
      "group": "鋼鐵",
      "type": "上市",
      "price": 25.15,
      "ma5": 25.23,
      "ma10": 25.1,
      "changeRate": -0.79,
      "isValid": true,
      "note": "拉回佈局 & Strict-VCP / MA300 20.05",
      "buy_price": 25.15,
      "latest_price": 25.15,
      "roi": 0.0,
      "daily_change": -0.79,
      "perf_1d": null,
      "perf_5d": null,
      "perf_10d": null,
      "perf_20d": null,
      "perf_30d": null,
      "perf_60d": null,
      "perf_120d": null
    },
    {
      "id": "2014",
      "name": "中鴻",
      "group": "鋼鐵",
      "type": "上市",
      "price": 18.5,
      "ma5": 18.62,
      "ma10": 18.47,
      "changeRate": -1.07,
      "isValid": true,
      "note": "拉回佈局 & Strict-VCP / MA300 16.99",
      "buy_price": 18.5,
      "latest_price": 18.5,
      "roi": 0.0,
      "daily_change": -1.07,
      "perf_1d": null,
      "perf_5d": null,
      "perf_10d": null,
      "perf_20d": null,
      "perf_30d": null,
      "perf_60d": null,
      "perf_120d": null
    },
    {
      "id": "2419",
      "name": "仲琦",
      "group": "通訊設備",
      "type": "上市",
      "price": 35.0,
      "ma5": 35.5,
      "ma10": 34.85,
      "changeRate": 1.89,
      "isValid": true,
      "note": "拉回佈局 / MA300 25.32",
      "buy_price": 35.0,
      "latest_price": 35.0,
      "roi": 0.0,
      "daily_change": 1.89,
      "perf_1d": null,
      "perf_5d": null,
      "perf_10d": null,
      "perf_20d": null,
      "perf_30d": null,
      "perf_60d": null,
      "perf_120d": null
    },
    {
      "id": "2548",
      "name": "華固",
      "group": "營建",
      "type": "上市",
      "price": 129.5,
      "ma5": 128.2,
      "ma10": 125.5,
      "changeRate": 0.39,
      "isValid": true,
      "note": "拉回佈局 & Strict-VCP / MA300 103.42",
      "buy_price": 129.5,
      "latest_price": 129.5,
      "roi": 0.0,
      "daily_change": 0.39,
      "perf_1d": null,
      "perf_5d": null,
      "perf_10d": null,
      "perf_20d": null,
      "perf_30d": null,
      "perf_60d": null,
      "perf_120d": null
    },
    {
      "id": "2838",
      "name": "聯邦銀",
      "group": "銀行",
      "type": "上市",
      "price": 21.05,
      "ma5": 20.96,
      "ma10": 20.86,
      "changeRate": 0.0,
      "isValid": true,
      "note": "拉回佈局 & Strict-VCP / MA300 17.35",
      "buy_price": 21.05,
      "latest_price": 21.05,
      "roi": 0.0,
      "daily_change": 0.0,
      "perf_1d": null,
      "perf_5d": null,
      "perf_10d": null,
      "perf_20d": null,
      "perf_30d": null,
      "perf_60d": null,
      "perf_120d": null
    },
    {
      "id": "2851",
      "name": "中再保",
      "group": "保險",
      "type": "上市",
      "price": 31.3,
      "ma5": 31.38,
      "ma10": 31.07,
      "changeRate": -1.57,
      "isValid": true,
      "note": "Strict-VCP / MA300 25.18",
      "buy_price": 31.3,
      "latest_price": 31.3,
      "roi": 0.0,
      "daily_change": -1.57,
      "perf_1d": null,
      "perf_5d": null,
      "perf_10d": null,
      "perf_20d": null,
      "perf_30d": null,
      "perf_60d": null,
      "perf_120d": null
    },
    {
      "id": "2880",
      "name": "華南金",
      "group": "金控",
      "type": "上市",
      "price": 36.05,
      "ma5": 34.75,
      "ma10": 34.24,
      "changeRate": 3.0,
      "isValid": true,
      "note": "Strict-VCP / MA300 28.87",
      "buy_price": 36.05,
      "latest_price": 36.05,
      "roi": 0.0,
      "daily_change": 3.0,
      "perf_1d": null,
      "perf_5d": null,
      "perf_10d": null,
      "perf_20d": null,
      "perf_30d": null,
      "perf_60d": null,
      "perf_120d": null
    },
    {
      "id": "2883",
      "name": "凱基金",
      "group": "金控",
      "type": "上市",
      "price": 20.75,
      "ma5": 21.02,
      "ma10": 20.59,
      "changeRate": -0.48,
      "isValid": true,
      "note": "拉回佈局 / MA300 16.56",
      "buy_price": 20.75,
      "latest_price": 20.75,
      "roi": 0.0,
      "daily_change": -0.48,
      "perf_1d": null,
      "perf_5d": null,
      "perf_10d": null,
      "perf_20d": null,
      "perf_30d": null,
      "perf_60d": null,
      "perf_120d": null
    },
    {
      "id": "2890",
      "name": "永豐金",
      "group": "金控",
      "type": "上市",
      "price": 33.3,
      "ma5": 33.0,
      "ma10": 32.42,
      "changeRate": 0.3,
      "isValid": true,
      "note": "拉回佈局 / MA300 24.97",
      "buy_price": 33.3,
      "latest_price": 33.3,
      "roi": 0.0,
      "daily_change": 0.3,
      "perf_1d": null,
      "perf_5d": null,
      "perf_10d": null,
      "perf_20d": null,
      "perf_30d": null,
      "perf_60d": null,
      "perf_120d": null
    },
    {
      "id": "3010",
      "name": "華立",
      "group": "IC-通路",
      "type": "上市",
      "price": 135.0,
      "ma5": 132.7,
      "ma10": 126.85,
      "changeRate": 0.0,
      "isValid": true,
      "note": "N字形 / MA300 104.1",
      "buy_price": 135.0,
      "latest_price": 135.0,
      "roi": 0.0,
      "daily_change": 0.0,
      "perf_1d": null,
      "perf_5d": null,
      "perf_10d": null,
      "perf_20d": null,
      "perf_30d": null,
      "perf_60d": null,
      "perf_120d": null
    },
    {
      "id": "3380",
      "name": "明泰",
      "group": "網通",
      "type": "上市",
      "price": 38.9,
      "ma5": 39.32,
      "ma10": 38.23,
      "changeRate": 1.83,
      "isValid": true,
      "note": "拉回佈局 / MA300 30.45",
      "buy_price": 38.9,
      "latest_price": 38.9,
      "roi": 0.0,
      "daily_change": 1.83,
      "perf_1d": null,
      "perf_5d": null,
      "perf_10d": null,
      "perf_20d": null,
      "perf_30d": null,
      "perf_60d": null,
      "perf_120d": null
    },
    {
      "id": "4526",
      "name": "東台",
      "group": "電機",
      "type": "上市",
      "price": 34.2,
      "ma5": 34.97,
      "ma10": 34.17,
      "changeRate": -1.01,
      "isValid": true,
      "note": "拉回佈局 / MA300 31.14",
      "buy_price": 34.2,
      "latest_price": 34.2,
      "roi": 0.0,
      "daily_change": -1.01,
      "perf_1d": null,
      "perf_5d": null,
      "perf_10d": null,
      "perf_20d": null,
      "perf_30d": null,
      "perf_60d": null,
      "perf_120d": null
    },
    {
      "id": "4755",
      "name": "三福化",
      "group": "化學工業",
      "type": "上市",
      "price": 152.0,
      "ma5": 143.7,
      "ma10": 141.25,
      "changeRate": 5.19,
      "isValid": true,
      "note": "Strict-VCP / MA300 116.76",
      "buy_price": 152.0,
      "latest_price": 152.0,
      "roi": 0.0,
      "daily_change": 5.19,
      "perf_1d": null,
      "perf_5d": null,
      "perf_10d": null,
      "perf_20d": null,
      "perf_30d": null,
      "perf_60d": null,
      "perf_120d": null
    },
    {
      "id": "6153",
      "name": "嘉聯益",
      "group": "PCB-製造",
      "type": "上市",
      "price": 17.65,
      "ma5": 17.42,
      "ma10": 16.85,
      "changeRate": 1.15,
      "isValid": true,
      "note": "拉回佈局 / MA300 14.55",
      "buy_price": 17.65,
      "latest_price": 17.65,
      "roi": 0.0,
      "daily_change": 1.15,
      "perf_1d": null,
      "perf_5d": null,
      "perf_10d": null,
      "perf_20d": null,
      "perf_30d": null,
      "perf_60d": null,
      "perf_120d": null
    },
    {
      "id": "3317",
      "name": "尼克森",
      "group": "IC-設計",
      "type": "上櫃",
      "price": 50.8,
      "ma5": 50.84,
      "ma10": 50.55,
      "changeRate": -0.39,
      "isValid": true,
      "note": "拉回佈局 / MA300 43.64",
      "buy_price": 50.8,
      "latest_price": 50.8,
      "roi": 0.0,
      "daily_change": -0.39,
      "perf_1d": null,
      "perf_5d": null,
      "perf_10d": null,
      "perf_20d": null,
      "perf_30d": null,
      "perf_60d": null,
      "perf_120d": null
    },
    {
      "id": "4768",
      "name": "晶呈科技",
      "group": "化學工業",
      "type": "上櫃",
      "price": 484.0,
      "ma5": 481.9,
      "ma10": 462.9,
      "changeRate": 0.41,
      "isValid": true,
      "note": "拉回佈局 / MA300 221.09",
      "buy_price": 484.0,
      "latest_price": 484.0,
      "roi": 0.0,
      "daily_change": 0.41,
      "perf_1d": null,
      "perf_5d": null,
      "perf_10d": null,
      "perf_20d": null,
      "perf_30d": null,
      "perf_60d": null,
      "perf_120d": null
    },
    {
      "id": "5864",
      "name": "致和證",
      "group": "證券",
      "type": "上櫃",
      "price": 25.35,
      "ma5": 24.32,
      "ma10": 23.99,
      "changeRate": 1.81,
      "isValid": true,
      "note": "Strict-VCP / MA300 15.65",
      "buy_price": 25.35,
      "latest_price": 25.35,
      "roi": 0.0,
      "daily_change": 1.81,
      "perf_1d": null,
      "perf_5d": null,
      "perf_10d": null,
      "perf_20d": null,
      "perf_30d": null,
      "perf_60d": null,
      "perf_120d": null
    },
    {
      "id": "6788",
      "name": "華景電",
      "group": "IC-半導體設備",
      "type": "上櫃",
      "price": 389.0,
      "ma5": 383.0,
      "ma10": 377.25,
      "changeRate": -0.77,
      "isValid": true,
      "note": "拉回佈局 / MA300 254.77",
      "buy_price": 389.0,
      "latest_price": 389.0,
      "roi": 0.0,
      "daily_change": -0.77,
      "perf_1d": null,
      "perf_5d": null,
      "perf_10d": null,
      "perf_20d": null,
      "perf_30d": null,
      "perf_60d": null,
      "perf_120d": null
    }
  ]
}