{
  "date": "2026/06/09 10:15:24",
  "source": "GitHub Actions",
  "list": [
    {
      "id": "1709",
      "name": "和益",
      "group": "化學工業",
      "type": "上市",
      "price": 20.3,
      "ma5": 20.27,
      "ma10": 19.88,
      "changeRate": 1.5,
      "isValid": true,
      "note": "拉回佈局 / MA300 17.33",
      "buy_price": 20.3,
      "latest_price": 20.3,
      "roi": 0.0,
      "daily_change": 1.5,
      "perf_1d": null,
      "perf_5d": null,
      "perf_10d": null,
      "perf_20d": null,
      "perf_30d": null,
      "perf_60d": null,
      "perf_120d": null
    },
    {
      "id": "2330",
      "name": "台積電",
      "group": "IC-代工",
      "type": "上市",
      "price": 2305.0,
      "ma5": 2355.0,
      "ma10": 2346.0,
      "changeRate": 0.44,
      "isValid": true,
      "note": "Strict-VCP / MA300 1446.86",
      "buy_price": 2305.0,
      "latest_price": 2305.0,
      "roi": 0.0,
      "daily_change": 0.44,
      "perf_1d": null,
      "perf_5d": null,
      "perf_10d": null,
      "perf_20d": null,
      "perf_30d": null,
      "perf_60d": null,
      "perf_120d": null
    },
    {
      "id": "2347",
      "name": "聯強",
      "group": "IC-通路",
      "type": "上市",
      "price": 89.4,
      "ma5": 88.8,
      "ma10": 87.95,
      "changeRate": 4.81,
      "isValid": true,
      "note": "N字形 / MA300 67.73",
      "buy_price": 89.4,
      "latest_price": 89.4,
      "roi": 0.0,
      "daily_change": 4.81,
      "perf_1d": null,
      "perf_5d": null,
      "perf_10d": null,
      "perf_20d": null,
      "perf_30d": null,
      "perf_60d": null,
      "perf_120d": null
    },
    {
      "id": "2379",
      "name": "瑞昱",
      "group": "IC-設計",
      "type": "上市",
      "price": 628.0,
      "ma5": 627.4,
      "ma10": 617.8,
      "changeRate": 5.37,
      "isValid": true,
      "note": "N字形 / MA300 518.46",
      "buy_price": 628.0,
      "latest_price": 628.0,
      "roi": 0.0,
      "daily_change": 5.37,
      "perf_1d": null,
      "perf_5d": null,
      "perf_10d": null,
      "perf_20d": null,
      "perf_30d": null,
      "perf_60d": null,
      "perf_120d": null
    },
    {
      "id": "2476",
      "name": "鉅祥",
      "group": "連接元件",
      "type": "上市",
      "price": 124.0,
      "ma5": 121.2,
      "ma10": 122.0,
      "changeRate": 5.08,
      "isValid": true,
      "note": "Strict-VCP / MA300 88.94",
      "buy_price": 124.0,
      "latest_price": 124.0,
      "roi": 0.0,
      "daily_change": 5.08,
      "perf_1d": null,
      "perf_5d": null,
      "perf_10d": null,
      "perf_20d": null,
      "perf_30d": null,
      "perf_60d": null,
      "perf_120d": null
    },
    {
      "id": "2603",
      "name": "長榮",
      "group": "航運",
      "type": "上市",
      "price": 223.0,
      "ma5": 230.4,
      "ma10": 224.25,
      "changeRate": -0.45,
      "isValid": true,
      "note": "拉回佈局 / MA300 195.53",
      "buy_price": 223.0,
      "latest_price": 223.0,
      "roi": 0.0,
      "daily_change": -0.45,
      "perf_1d": null,
      "perf_5d": null,
      "perf_10d": null,
      "perf_20d": null,
      "perf_30d": null,
      "perf_60d": null,
      "perf_120d": null
    },
    {
      "id": "2637",
      "name": "慧洋-KY",
      "group": "航運",
      "type": "上市",
      "price": 80.0,
      "ma5": 78.84,
      "ma10": 77.79,
      "changeRate": 1.91,
      "isValid": true,
      "note": "拉回佈局 / MA300 64.78",
      "buy_price": 80.0,
      "latest_price": 80.0,
      "roi": 0.0,
      "daily_change": 1.91,
      "perf_1d": null,
      "perf_5d": null,
      "perf_10d": null,
      "perf_20d": null,
      "perf_30d": null,
      "perf_60d": null,
      "perf_120d": null
    },
    {
      "id": "2891",
      "name": "中信金",
      "group": "金控",
      "type": "上市",
      "price": 68.0,
      "ma5": 67.7,
      "ma10": 64.37,
      "changeRate": 3.98,
      "isValid": true,
      "note": "N字形 / MA300 45.69",
      "buy_price": 68.0,
      "latest_price": 68.0,
      "roi": 0.0,
      "daily_change": 3.98,
      "perf_1d": null,
      "perf_5d": null,
      "perf_10d": null,
      "perf_20d": null,
      "perf_30d": null,
      "perf_60d": null,
      "perf_120d": null
    },
    {
      "id": "3023",
      "name": "信邦",
      "group": "連接元件",
      "type": "上市",
      "price": 325.5,
      "ma5": 321.5,
      "ma10": 316.85,
      "changeRate": 0.93,
      "isValid": true,
      "note": "拉回佈局 / MA300 233.05",
      "buy_price": 325.5,
      "latest_price": 325.5,
      "roi": 0.0,
      "daily_change": 0.93,
      "perf_1d": null,
      "perf_5d": null,
      "perf_10d": null,
      "perf_20d": null,
      "perf_30d": null,
      "perf_60d": null,
      "perf_120d": null
    },
    {
      "id": "3026",
      "name": "禾伸堂",
      "group": "被動元件",
      "type": "上市",
      "price": 639.0,
      "ma5": 625.6,
      "ma10": 630.4,
      "changeRate": 6.32,
      "isValid": true,
      "note": "N字形 / MA300 134.64",
      "buy_price": 639.0,
      "latest_price": 639.0,
      "roi": 0.0,
      "daily_change": 6.32,
      "perf_1d": null,
      "perf_5d": null,
      "perf_10d": null,
      "perf_20d": null,
      "perf_30d": null,
      "perf_60d": null,
      "perf_120d": null
    },
    {
      "id": "3356",
      "name": "奇偶",
      "group": "安全監控",
      "type": "上市",
      "price": 60.2,
      "ma5": 59.36,
      "ma10": 59.23,
      "changeRate": 1.86,
      "isValid": true,
      "note": "拉回佈局 / MA300 46.25",
      "buy_price": 60.2,
      "latest_price": 60.2,
      "roi": 0.0,
      "daily_change": 1.86,
      "perf_1d": null,
      "perf_5d": null,
      "perf_10d": null,
      "perf_20d": null,
      "perf_30d": null,
      "perf_60d": null,
      "perf_120d": null
    },
    {
      "id": "4904",
      "name": "遠傳",
      "group": "電信服務",
      "type": "上市",
      "price": 103.0,
      "ma5": 101.6,
      "ma10": 98.57,
      "changeRate": 1.98,
      "isValid": true,
      "note": "拉回佈局 / MA300 88.89",
      "buy_price": 103.0,
      "latest_price": 103.0,
      "roi": 0.0,
      "daily_change": 1.98,
      "perf_1d": null,
      "perf_5d": null,
      "perf_10d": null,
      "perf_20d": null,
      "perf_30d": null,
      "perf_60d": null,
      "perf_120d": null
    },
    {
      "id": "6196",
      "name": "帆宣",
      "group": "儀器設備工程",
      "type": "上市",
      "price": 508.0,
      "ma5": 502.7,
      "ma10": 505.05,
      "changeRate": 4.21,
      "isValid": true,
      "note": "N字形 / MA300 253.68",
      "buy_price": 508.0,
      "latest_price": 508.0,
      "roi": 0.0,
      "daily_change": 4.21,
      "perf_1d": null,
      "perf_5d": null,
      "perf_10d": null,
      "perf_20d": null,
      "perf_30d": null,
      "perf_60d": null,
      "perf_120d": null
    },
    {
      "id": "6672",
      "name": "騰輝電子-KY",
      "group": "PCB-製造",
      "type": "上市",
      "price": 219.5,
      "ma5": 218.9,
      "ma10": 217.9,
      "changeRate": 1.15,
      "isValid": true,
      "note": "N字形 / MA300 101.5",
      "buy_price": 219.5,
      "latest_price": 219.5,
      "roi": 0.0,
      "daily_change": 1.15,
      "perf_1d": null,
      "perf_5d": null,
      "perf_10d": null,
      "perf_20d": null,
      "perf_30d": null,
      "perf_60d": null,
      "perf_120d": null
    },
    {
      "id": "8473",
      "name": "山林水",
      "group": "綠能環保",
      "type": "上市",
      "price": 54.5,
      "ma5": 54.16,
      "ma10": 52.14,
      "changeRate": 1.11,
      "isValid": true,
      "note": "N字形 / MA300 35.85",
      "buy_price": 54.5,
      "latest_price": 54.5,
      "roi": 0.0,
      "daily_change": 1.11,
      "perf_1d": null,
      "perf_5d": null,
      "perf_10d": null,
      "perf_20d": null,
      "perf_30d": null,
      "perf_60d": null,
      "perf_120d": null
    },
    {
      "id": "9933",
      "name": "中鼎",
      "group": "其他",
      "type": "上市",
      "price": 41.4,
      "ma5": 42.3,
      "ma10": 40.84,
      "changeRate": -0.96,
      "isValid": true,
      "note": "拉回佈局 / MA300 31.14",
      "buy_price": 41.4,
      "latest_price": 41.4,
      "roi": 0.0,
      "daily_change": -0.96,
      "perf_1d": null,
      "perf_5d": null,
      "perf_10d": null,
      "perf_20d": null,
      "perf_30d": null,
      "perf_60d": null,
      "perf_120d": null
    },
    {
      "id": "3537",
      "name": "堡達",
      "group": "IC-通路",
      "type": "上櫃",
      "price": 80.2,
      "ma5": 79.16,
      "ma10": 77.15,
      "changeRate": 4.56,
      "isValid": true,
      "note": "N字形 / MA300 45.98",
      "buy_price": 80.2,
      "latest_price": 80.2,
      "roi": 0.0,
      "daily_change": 4.56,
      "perf_1d": null,
      "perf_5d": null,
      "perf_10d": null,
      "perf_20d": null,
      "perf_30d": null,
      "perf_60d": null,
      "perf_120d": null
    },
    {
      "id": "4167",
      "name": "松瑞藥",
      "group": "生技",
      "type": "上櫃",
      "price": 20.1,
      "ma5": 20.36,
      "ma10": 20.0,
      "changeRate": -1.23,
      "isValid": true,
      "note": "拉回佈局 / MA300 18.98",
      "buy_price": 20.1,
      "latest_price": 20.1,
      "roi": 0.0,
      "daily_change": -1.23,
      "perf_1d": null,
      "perf_5d": null,
      "perf_10d": null,
      "perf_20d": null,
      "perf_30d": null,
      "perf_60d": null,
      "perf_120d": null
    },
    {
      "id": "4707",
      "name": "磐亞",
      "group": "化學工業",
      "type": "上櫃",
      "price": 20.2,
      "ma5": 20.07,
      "ma10": 18.4,
      "changeRate": 4.94,
      "isValid": true,
      "note": "N字形 / MA300 10.86",
      "buy_price": 20.2,
      "latest_price": 20.2,
      "roi": 0.0,
      "daily_change": 4.94,
      "perf_1d": null,
      "perf_5d": null,
      "perf_10d": null,
      "perf_20d": null,
      "perf_30d": null,
      "perf_60d": null,
      "perf_120d": null
    },
    {
      "id": "5410",
      "name": "國眾",
      "group": "資訊通路",
      "type": "上櫃",
      "price": 40.2,
      "ma5": 39.95,
      "ma10": 40.0,
      "changeRate": 2.42,
      "isValid": true,
      "note": "N字形 / MA300 31.18",
      "buy_price": 40.2,
      "latest_price": 40.2,
      "roi": 0.0,
      "daily_change": 2.42,
      "perf_1d": null,
      "perf_5d": null,
      "perf_10d": null,
      "perf_20d": null,
      "perf_30d": null,
      "perf_60d": null,
      "perf_120d": null
    },
    {
      "id": "5536",
      "name": "聖暉*",
      "group": "儀器設備工程",
      "type": "上櫃",
      "price": 1080.0,
      "ma5": 1087.0,
      "ma10": 1057.6,
      "changeRate": 2.86,
      "isValid": true,
      "note": "拉回佈局 / MA300 652.68",
      "buy_price": 1080.0,
      "latest_price": 1080.0,
      "roi": 0.0,
      "daily_change": 2.86,
      "perf_1d": null,
      "perf_5d": null,
      "perf_10d": null,
      "perf_20d": null,
      "perf_30d": null,
      "perf_60d": null,
      "perf_120d": null
    },
    {
      "id": "6548",
      "name": "長科*",
      "group": "IC-導線架",
      "type": "上櫃",
      "price": 90.0,
      "ma5": 89.9,
      "ma10": 80.13,
      "changeRate": 9.09,
      "isValid": true,
      "note": "N字形 / MA300 41.06",
      "buy_price": 90.0,
      "latest_price": 90.0,
      "roi": 0.0,
      "daily_change": 9.09,
      "perf_1d": null,
      "perf_5d": null,
      "perf_10d": null,
      "perf_20d": null,
      "perf_30d": null,
      "perf_60d": null,
      "perf_120d": null
    }
  ]
}